{
    "airidasž.": {
        "modifier": 58310
    },
    "andrejusi.": {
        "modifier": 0,
        "runningRecordKm": 1016.26,
        "runningRecordYear": 2022,
        "isRunningTop3Ever": true
    },
    "aleksandrasn.": {
        "modifier": 0
    },
    "aurimass.": {
        "modifier": 4860,
        "runningRecordKm": 8.31,
        "runningRecordYear": 2022
    },
    "cristinam.": {
        "modifier": 0,
        "runningRecordKm": 200.82,
        "runningRecordYear": 2023
    },
    "dariuso.": {
        "modifier": 9020,
        "runningRecordKm": 500.05,
        "runningRecordYear": 2022,
        "isRunningTop3Ever": true
    },
    "deimantės.": {
        "modifier": 0
    },
    "dovilėb.": {
        "modifier": 8640
    },
    "dominykasr.": {
        "modifier": 0,
        "runningRecordKm": 15.05,
        "runningRecordYear": 2023
    },
    "edvinasv.": {
        "modifier": 72080,
        "runningRecordKm": 80.05,
        "runningRecordYear": 2020
    },
    "edgarasa.": {
        "modifier": 145430,
        "runningRecordKm": 1249.96,
        "runningRecordYear": 2019,
        "isRunningTop3Ever": true
    },
    "egidijusr.": {
        "modifier": 0,
        "runningRecordKm": 76.16,
        "runningRecordYear": 2022
    },
    "elektrinisp.": {
        "modifier": 0
    },
    "erniukasb.": {
        "modifier": 246230,
        "runningRecordKm": 1126.65,
        "runningRecordYear": 2021,
        "isRunningTop3Ever": true
    },
    "ferl.": {
        "modifier": 2550,
        "runningRecordKm": 17.49,
        "runningRecordYear": 2023
    },
    "johanh.": {
        "modifier": 9020,
        "runningRecordKm": 52.59,
        "runningRecordYear": 2023
    },
    "justasb.": {
        "modifier": 0
    },
    "justinaslaaaaa.": {
        "modifier": 73950,
        "runningRecordKm": 146.89,
        "runningRecordYear": 2023
    },
    "karolisv.": {
        "modifier": 0,
        "runningRecordKm": 11.41,
        "runningRecordYear": 2022
    },
    "klaidasp.": {
        "modifier": 10380,
        "runningRecordKm": 410.37,
        "runningRecordYear": 2021
    },
    "laimonasm.": {
        "modifier": 0,
        "runningRecordKm": 159.57,
        "runningRecordYear": 2017,
        "isRunningTop3Ever": true
    },
    "lukasa.": {
        "modifier": 0
    },
    "mantasr.": {
        "modifier": 25350,
        "runningRecordKm": 201.2,
        "runningRecordYear": 2023
    },
    "matast.": {
        "modifier": 0,
        "runningRecordKm": 19.1,
        "runningRecordYear": 2023
    },
    "mindaugass.": {
        "modifier": 0,
        "runningRecordKm": 129.62,
        "runningRecordYear": 2023
    },
    "martynasj.": {
        "modifier": 50080,
        "runningRecordKm": 1002.36,
        "runningRecordYear": 2020,
        "isRunningTop3Ever": true
    },
    "oļegsč.": {
        "modifier": 0
    },
    "petern.": {
        "modifier": 54047,
        "runningRecordKm": 271.38,
        "runningRecordYear": 2017,
        "isRunningTop3Ever": true
    },
    "raimondap.": {
        "modifier": 9030,
        "runningRecordKm": 100.02,
        "runningRecordYear": 2023
    },
    "robertask.": {
        "modifier": 0
    },
    "rokasj.": {
        "modifier": 9260
    },
    "rytisj.": {
        "modifier": 0,
        "runningRecordKm": 52.42,
        "runningRecordYear": 2023
    },
    "rokass.": {
        "modifier": 7100,
        "runningRecordKm": 75.18,
        "runningRecordYear": 2022
    },
    "rokassidaravicius.": {
        "modifier": 2697,
        "runningRecordKm": 82.17,
        "runningRecordYear": 2021
    },
    "sandraž.": {
        "modifier": 10560,
        "runningRecordKm": 13,
        "runningRecordYear": 2021
    },
    "simasv.": {
        "modifier": 106770,
        "runningRecordKm": 216.17,
        "runningRecordYear": 2022
    },
    "tadask.": {
        "modifier": 12340,
        "runningRecordKm": 101.3,
        "runningRecordYear": 2023
    },
    "tadast.": {
        "modifier": 10010
    },
    "tamásk.": {
        "modifier": 7110,
        "runningRecordKm": 100.38,
        "runningRecordYear": 2023
    },
    "tomasb.": {
        "modifier": 11100,
        "runningRecordKm": 143.43,
        "runningRecordYear": 2022
    },
    "tomasr.": {
        "modifier": 68020
    },
    "vaidas.": {
        "modifier": 60840,
        "runningRecordKm": 500.12,
        "runningRecordYear": 2023,
        "isRunningTop3Ever": true
    },
    "žydrūnasg.": {
        "modifier": 39130
    },
    "linav.": {
        "modifier": 11300
    },
    "justasp.": {
        "modifier": 0
    }
}